Metadata-Version: 1.0
Name: qs-distributions
Version: 0.1
Summary: Gaussian and Binomial distributions
Home-page: UNKNOWN
Author: Quintin Sheridan
Author-email: qsherida@alumni.nd.edu
License: UNKNOWN
Platform: UNKNOWN
